{"name":"build-javascript","namedChunkGroups":{"app":{"name":"app","assets":[{"name":"webpack-runtime-aac583f01caab7eb873b.js","size":3563},{"name":"framework-4196b388e9eb81dab12b.js","size":140322},{"name":"styles.8feb71c31e30c70b8460.css","size":8132},{"name":"app-324a19f1a1f901ae0e1f.js","size":67738}],"filteredAssets":0,"assetsSize":219755,"filteredAuxiliaryAssets":3,"auxiliaryAssetsSize":606553},"component---src-pages-404-js":{"name":"component---src-pages-404-js","assets":[{"name":"component---src-pages-404-js-da5185bc98a7d31a6dc9.js","size":755}],"filteredAssets":0,"assetsSize":755,"filteredAuxiliaryAssets":1,"auxiliaryAssetsSize":1746},"component---src-pages-index-js":{"name":"component---src-pages-index-js","assets":[{"name":"component---src-pages-index-js-a3c95ca74833c1fa7da8.js","size":12052}],"filteredAssets":0,"assetsSize":12052,"filteredAuxiliaryAssets":1,"auxiliaryAssetsSize":28336}},"assetsByChunkName":{"app":["webpack-runtime-aac583f01caab7eb873b.js","framework-4196b388e9eb81dab12b.js","styles.8feb71c31e30c70b8460.css","app-324a19f1a1f901ae0e1f.js"],"component---src-pages-404-js":["component---src-pages-404-js-da5185bc98a7d31a6dc9.js"],"component---src-pages-index-js":["component---src-pages-index-js-a3c95ca74833c1fa7da8.js"]},"childAssetsByChunkName":{}}